sphinx_cldomain_theme/__init__.py
sphinx_cldomain_theme/__pycache__/__init__.cpython-39.pyc
sphinx_cldomain_theme/cldomain/layout.html
sphinx_cldomain_theme/cldomain/reference.html
sphinx_cldomain_theme/cldomain/relations.html
sphinx_cldomain_theme/cldomain/theme.conf
sphinx_cldomain_theme/cldomain/static/cldomain.css_t
sphinx_cldomain_theme/cldomain/static/pygments.css
sphinx_cldomain_theme-0.0.1.dist-info/LICENSE
sphinx_cldomain_theme-0.0.1.dist-info/METADATA
sphinx_cldomain_theme-0.0.1.dist-info/WHEEL
sphinx_cldomain_theme-0.0.1.dist-info/entry_points.txt
sphinx_cldomain_theme-0.0.1.dist-info/top_level.txt
sphinx_cldomain_theme-0.0.1.dist-info/RECORD
