Metadata-Version: 2.1
Name: sphinx-cldomain-theme
Version: 0.0.1
Summary: Sphinx Common Lisp Domain Theme
Author-email: Russell Sim <rsl@simopolis.xyz>
License: MIT
Project-URL: Homepage, https://sr.ht/~rsl/sphinxcontrib-cldomain/
Project-URL: Bug Reports, https://todo.sr.ht/~rsl/sphinxcontrib-cldomain
Project-URL: Source, https://git.sr.ht/~rsl/sphinx-cldomain-theme
Classifier: Intended Audience :: Developers
Classifier: License :: OSI Approved :: MIT License
Classifier: Natural Language :: English
Classifier: Operating System :: OS Independent
Classifier: Programming Language :: Python
Classifier: Topic :: Internet
Classifier: Topic :: Software Development :: Documentation
Requires-Python: >=3.7
License-File: LICENSE
Requires-Dist: sphinx
